asf/__init__.py
asf/py.typed
asf/analysis/__init__.py
asf/analysis/features_analysis.py
asf/analysis/performance_analysis.py
asf/cli/__init__.py
asf/cli/cli_train.py
asf/clustering/__init__.py
asf/clustering/wrappers.py
asf/epm/__init__.py
asf/epm/epm.py
asf/epm/epm_tuner.py
asf/metrics/__init__.py
asf/metrics/baselines.py
asf/metrics/par10.py
asf/pre_selector/__init__.py
asf/pre_selector/abstract_pre_selector.py
asf/pre_selector/beam_search_pre_selection.py
asf/pre_selector/brute_force_pre_selection.py
asf/pre_selector/genetic_algorithm_pre_selection.py
asf/pre_selector/knee_of_the_curve_pre_selector.py
asf/pre_selector/marginal_contribution_based.py
asf/pre_selector/optimize_pre_selection.py
asf/pre_selector/random_local_search_pre_selection.py
asf/pre_selector/sbs_pre_selection.py
asf/predictors/__init__.py
asf/predictors/abstract_predictor.py
asf/predictors/epm_extra_trees.py
asf/predictors/epm_random_forest.py
asf/predictors/linear_model.py
asf/predictors/mlp.py
asf/predictors/random_forest.py
asf/predictors/ranking_mlp.py
asf/predictors/regression_mlp.py
asf/predictors/ridge.py
asf/predictors/sklearn_wrapper.py
asf/predictors/survival.py
asf/predictors/svm.py
asf/predictors/xgboost.py
asf/predictors/utils/datasets.py
asf/predictors/utils/losses.py
asf/predictors/utils/mlp.py
asf/preprocessing/__init__.py
asf/preprocessing/feature_group_selector.py
asf/preprocessing/performance_scaling.py
asf/preprocessing/quadratic_expansion.py
asf/preprocessing/schmee_hahn_imputer.py
asf/preprocessing/sklearn_preprocessor.py
asf/presolving/__init__.py
asf/presolving/asap_v2.py
asf/presolving/aspeed.py
asf/presolving/configurable_presolver.py
asf/presolving/greedy_presolver.py
asf/presolving/presolver.py
asf/presolving/static_3s.py
asf/presolving/submodular_presolver.py
asf/scenario/__init__.py
asf/scenario/aslib_reader.py
asf/scenario/epmbench_reader.py
asf/selectors/__init__.py
asf/selectors/abstract_epm_based_selector.py
asf/selectors/abstract_model_based_selector.py
asf-0.1.4.dist-info/licenses/LICENSE
asf-0.1.4.dist-info/METADATA
asf-0.1.4.dist-info/WHEEL
asf-0.1.4.dist-info/top_level.txt
asf-0.1.4.dist-info/RECORD
