Metadata-Version: 2.4
Name: asf
Version: 0.1.4
Summary: Algorithm selection framework
Author-email: Hadar Shavit <shavit@aim.rwth-aachen.de>
Maintainer-email: Hadar Shavit <shavit@aim.rwth-aachen.de>
License: MIT License
Project-URL: documentation, https://hadarshavit.github.io/asf/latest/
Project-URL: repository, https://github.com/hadarshavit/asf
Classifier: Development Status :: 2 - Pre-Alpha
Classifier: Intended Audience :: Developers
Classifier: Intended Audience :: Science/Research
Classifier: Natural Language :: English
Classifier: License :: OSI Approved :: MIT License
Classifier: Operating System :: POSIX :: Linux
Classifier: Programming Language :: Python :: 3.10
Classifier: Programming Language :: Python :: 3.11
Classifier: Programming Language :: Python :: 3.12
Classifier: Programming Language :: Python :: 3.13
Classifier: Topic :: Scientific/Engineering :: Artificial Intelligence
Requires-Python: >=3.10
License-File: LICENSE
Requires-Dist: scikit-learn
Requires-Dist: pandas
Requires-Dist: numpy
Provides-Extra: aslib
Requires-Dist: pyyaml; extra == "aslib"
Requires-Dist: liac-arff; extra == "aslib"
Provides-Extra: nn
Requires-Dist: torch; extra == "nn"
Provides-Extra: xgb
Requires-Dist: xgboost; extra == "xgb"
Provides-Extra: tune
Requires-Dist: smac; extra == "tune"
Provides-Extra: aspeed
Requires-Dist: clingo; extra == "aspeed"
Provides-Extra: survival
Requires-Dist: scikit-survival; extra == "survival"
Provides-Extra: 3s
Requires-Dist: pulp; extra == "3s"
Provides-Extra: analysis
Requires-Dist: plotly; extra == "analysis"
Requires-Dist: scipy; extra == "analysis"
Provides-Extra: epmbench
Requires-Dist: fastparquet; extra == "epmbench"
Provides-Extra: dev
Requires-Dist: pytest; extra == "dev"
Requires-Dist: pytest-cov; extra == "dev"
Requires-Dist: ruff; extra == "dev"
Provides-Extra: all
Requires-Dist: pyyaml; extra == "all"
Requires-Dist: liac-arff; extra == "all"
Requires-Dist: torch; extra == "all"
Requires-Dist: xgboost; extra == "all"
Requires-Dist: smac; extra == "all"
Requires-Dist: clingo; extra == "all"
Requires-Dist: scikit-survival; extra == "all"
Requires-Dist: pulp; extra == "all"
Requires-Dist: plotly; extra == "all"
Requires-Dist: scipy; extra == "all"
Requires-Dist: fastparquet; extra == "all"
Dynamic: license-file
